pogodoc/__init__.py
pogodoc/sdk.py
pogodoc/test.py
pogodoc/utils.py
pogodoc/client/__init__.py
pogodoc/client/client.py
pogodoc/client/environment.py
pogodoc/client/core/__init__.py
pogodoc/client/core/api_error.py
pogodoc/client/core/client_wrapper.py
pogodoc/client/core/datetime_utils.py
pogodoc/client/core/file.py
pogodoc/client/core/force_multipart.py
pogodoc/client/core/http_client.py
pogodoc/client/core/http_response.py
pogodoc/client/core/jsonable_encoder.py
pogodoc/client/core/pydantic_utilities.py
pogodoc/client/core/query_encoder.py
pogodoc/client/core/remove_none_from_dict.py
pogodoc/client/core/request_options.py
pogodoc/client/core/serialization.py
pogodoc/client/documents/__init__.py
pogodoc/client/documents/client.py
pogodoc/client/documents/raw_client.py
pogodoc/client/documents/types/__init__.py
pogodoc/client/documents/types/get_job_status_response.py
pogodoc/client/documents/types/get_job_status_response_format_opts.py
pogodoc/client/documents/types/get_job_status_response_format_opts_format.py
pogodoc/client/documents/types/get_job_status_response_output.py
pogodoc/client/documents/types/get_job_status_response_output_data.py
pogodoc/client/documents/types/get_job_status_response_output_metadata.py
pogodoc/client/documents/types/initialize_render_job_request_format_opts.py
pogodoc/client/documents/types/initialize_render_job_request_format_opts_format.py
pogodoc/client/documents/types/initialize_render_job_request_target.py
pogodoc/client/documents/types/initialize_render_job_request_type.py
pogodoc/client/documents/types/initialize_render_job_response.py
pogodoc/client/documents/types/initialize_render_job_response_target.py
pogodoc/client/documents/types/start_immediate_render_request_format_opts.py
pogodoc/client/documents/types/start_immediate_render_request_format_opts_format.py
pogodoc/client/documents/types/start_immediate_render_request_target.py
pogodoc/client/documents/types/start_immediate_render_request_type.py
pogodoc-0.5.8.dist-info/licenses/LICENSE.md
pogodoc-0.5.8.dist-info/METADATA
pogodoc-0.5.8.dist-info/WHEEL
pogodoc-0.5.8.dist-info/top_level.txt
pogodoc-0.5.8.dist-info/RECORD
