Metadata-Version: 2.4
Name: pogodoc
Version: 0.5.8
Summary: Python SDK for Pogodoc
Project-URL: homepage, https://pogodoc.com
Project-URL: repository, https://github.com/pogodoc/pogodoc-py
Requires-Python: >=3.12
License-File: LICENSE.md
Requires-Dist: pydantic==2.11.4
Requires-Dist: httpx==0.25.1
Requires-Dist: stream-python
Dynamic: license-file
